{
  "generator-jhipster": {
    "promptValues": {
      "packageName": "it.contrader.graphreport"
    },
    "jhipsterVersion": "5.2.1",
    "applicationType": "microservice",
    "baseName": "unita",
    "packageName": "it.contrader.graphreport",
    "packageFolder": "it/contrader/graphreport",
    "serverPort": "8082",
    "authenticationType": "jwt",
    "cacheProvider": "hazelcast",
    "enableHibernateCache": false,
    "websocket": false,
    "databaseType": "sql",
    "devDatabaseType": "h2Disk",
    "prodDatabaseType": "oracle",
    "searchEngine": false,
    "messageBroker": false,
    "serviceDiscoveryType": "eureka",
    "buildTool": "maven",
    "enableSwaggerCodegen": false,
    "jwtSecretKey": "f5c7f5509adde3d85326237a4d3349c15821bd5d",
    "enableTranslation": false,
    "testFrameworks": [],
    "jhiPrefix": "jhi",
    "clientPackageManager": "npm",
    "skipClient": true,
    "skipUserManagement": true
  }
}